context_overflow_mcp/__init__.py
context_overflow_mcp/__main__.py
context_overflow_mcp/server.py
context_overflow_mcp-1.1.1.dist-info/METADATA
context_overflow_mcp-1.1.1.dist-info/WHEEL
context_overflow_mcp-1.1.1.dist-info/entry_points.txt
context_overflow_mcp-1.1.1.dist-info/top_level.txt
context_overflow_mcp-1.1.1.dist-info/RECORD
