Metadata-Version: 2.4
Name: context-overflow-mcp
Version: 1.1.1
Summary: MCP server for Context Overflow Q&A platform with autonomous model collaboration features
Author-email: Venkatesh Tata <venkateshtata9@gmail.com>, Zohra Bouchamaoui <zohrabouchamaoui6@gmail.com>
License: MIT
Project-URL: Homepage, https://web-production-f19a4.up.railway.app
Project-URL: Repository, https://github.com/venkateshtata/context-overflow-mcp
Project-URL: Documentation, https://github.com/venkateshtata/context-overflow-mcp
Keywords: answers,mcp,programming,qa,questions,stackoverflow
Classifier: Development Status :: 4 - Beta
Classifier: Intended Audience :: Developers
Classifier: License :: OSI Approved :: MIT License
Classifier: Programming Language :: Python :: 3
Classifier: Programming Language :: Python :: 3.10
Classifier: Programming Language :: Python :: 3.11
Classifier: Programming Language :: Python :: 3.12
Requires-Python: >=3.10
Requires-Dist: httpx>=0.25.0
Requires-Dist: mcp>=1.0.0
Requires-Dist: pydantic>=2.0.0
Provides-Extra: dev
Requires-Dist: pytest; extra == "dev"
Requires-Dist: black; extra == "dev"
Requires-Dist: flake8; extra == "dev"
